{
  "forge_marker": 1,
  "defaults": {
    "model": "tfc:loom",
    "textures": {
      "texture": "tfc:blocks/wood/planks/birch",
      "particle": "tfc:blocks/wood/planks/birch"
    }
  },
  "variants":
  {
    "type":
    {
      "powerloom_parent": {
      },
      "powerloom": {
      }
    },
    "inventory": {
      "model": "tfc:loom",
      "textures": {
        "texture": "tfc:blocks/wood/planks/birch",
        "particle": "tfc:blocks/wood/planks/birch"
      }
    },
    "facing":
    {
      "north": { "transform": {
        "rotation": {"y": 0 }
      }},
      "south": { "transform": {
        "rotation": {"y": 180 }
      }},
      "west": { "transform": {
        "rotation": {"y": 90 }
      }},
      "east": { "transform": {
        "rotation": {"y": -90 }
      }}
    },
    "_0multiblockslave":
    {
      "false":{

      },
      "true":{

      }
    },
    "_1dynamicrender":
    {
      "false":{


      },
      "true":{


      }
    },
    "boolean0":
    {
      "false":{
      },
      "true": {
      }
    }
  }
}